{"title":"「一本通 6.3 练习 2」聪明的燕姿","time_limit":1000,"memory_limit":512,"tags":[],"operation":{"submit":"https://loj.ac/problem/10207#submit_code","submissions":"https://loj.ac/submissions?problem_id=10207","statistics":"https://loj.ac/problem/10207/statistics/fastest","testdata":"https://loj.ac/problem/10207/testdata","discussion":"https://loj.ac/discussion/problem/10207"},"statement":[{"title":"题目描述","type":"description","format":"markdown","require":["katex"],"content":"**题目详见 [LOJ #2234](https://loj.ac/problem/2234)，本题关闭提交。**"}]}