{"title":"「PA 2019」A + B","time_limit":1000,"memory_limit":256,"tags":["2019","PA","数位 DP","DP"],"operation":{"submit":"https://loj.ac/problem/3214#submit_code","submissions":"https://loj.ac/submissions?problem_id=3214","statistics":"https://loj.ac/problem/3214/statistics/fastest","testdata":"https://loj.ac/problem/3214/testdata","discussion":"https://loj.ac/discussion/problem/3214"},"statement":[{"title":"题目描述","type":"description","format":"markdown","require":["katex"],"content":"**题目译自 [PA 2019](https://sio2.mimuw.edu.pl/c/pa-2019-1/dashboard/) Runda próbna [A + B](https://sio2.mimuw.edu.pl/c/pa-2019-1/p/apb/)，感谢 [@zimpha](https://github.com/zimpha) 提供 PA 2019 的题目翻译和官方数据。**\r\n\r\n在列竖式计算两个十进制数的和的时候，人们可能会错算成这样：\r\n\r\n![apb.png](https://loj-img.upyun.menci.memset0.cn/2019/12/18/5df9f3e351eb0.png)\r\n\r\n在图里的左边，$ 248 + 208 $ 被错算成了 $4416$。\r\n\r\n给定正整数 $ n $，问有多少对非负整数 $ a, b $ 满足 $ a + b $ 会被错算成 $ n $。\r\n\r\n注意：$ a $ 可以等于 $ b $，且 $ a = 1, b = 2 $ 和 $ a = 2, b = 1 $ 是两种不同的方案。"},{"title":"输入格式","type":"input_format","format":"markdown","require":["katex"],"content":"第一行包含一个正整数 $n$。\r\n"},{"title":"输出格式","type":"output_format","format":"markdown","require":["katex"],"content":"输出一个整数，即满足条件的 $ a, b $ 的数量。\r\n"},{"title":"样例","type":"example","format":"markdown","require":["katex"],"content":"#### 样例输入\r\n```plain\r\n112\r\n```\r\n\r\n#### 样例输出\r\n```plain\r\n50\r\n```\r\n"},{"title":"数据范围与提示","type":"limit_and_hint","format":"markdown","require":["katex"],"content":"对于 $100\\%$ 的数据，保证 $1 \\le n < 10^{18}$\r\n"}]}