{"title":"「LibreOJ β Round #3」绯色 IOI（抵达）","time_limit":1000,"memory_limit":256,"tags":["LibreOJ β Round","贪心","构造"],"operation":{"submit":"https://loj.ac/problem/521#submit_code","submissions":"https://loj.ac/submissions?problem_id=521","statistics":"https://loj.ac/problem/521/statistics/fastest","testdata":"https://loj.ac/problem/521/testdata","discussion":"https://loj.ac/discussion/problem/521"},"statement":[{"title":"题目描述","type":"description","format":"markdown","require":["katex"],"content":"> Jsp 很快解决了问题，Rlc 正要说什么，却见 Jsp 望向窗外。Rlc 心中一阵失落，顿时没了心情，低下头去默默流着眼泪。\r\n>\r\n> 不知过了多久， Rlc 被列车员的通报惊醒：「各位乘客，前方列车即将到达 Oli 国的首都 IlO 市。」Oli 国并不是 Jsp 和 Rlc 的目的地，不过这也让 Rlc 终于抓到了机会。\r\n>\r\n> 「Oli 国到了。」  \r\n> 「是啊 …… Oli 国 ……」  \r\n> 「据说曾经被评为地球上最和谐的国家之一呢，Jsp。」  \r\n> 「看起来和这个词没有任何关系？」  \r\n> 「是啊 …… 自从那次之后 ……」  \r\n> 「和你我又有什么关系呢？」  \r\n> 「也许吧。看着我，Jsp。」  \r\n> 「Rlc？」  \r\n> 「这三年你都做了什么呢？」    \r\n> 「OI。」  \r\n> 「接下来的两年呢？」  \r\n> 「……」  \r\n>\r\n> 二人相对无言，直到列车到达终点。\r\n\r\nOIi 国由 $n$ 个城市构成，从 $1$ 到 $n$ 编号，这 $n$ 个城市由 $n-1$ 条双向道路**连通**着。  \r\n其中每个城市的危险程度不同，城市按危险度从小到大排列为 $a_1,a_2,...,a_n$。  \r\n城市太过危险，所以每个城市需要有一个庇护所。**定义每个城市的庇护所为与它相连（不包括自身）的危险度最小的城市**，出于某种神秘的原因，**任意两个不同的城市庇护所不同**。\r\n\r\n可惜，中央政府领导人 \\*\\*\\*\\*\\*1317 忘了每个城市的危险度大小，也忘了每个城市庇护所的编号，只记得这些道路。  \r\n$a_1,a_2,...,a_n$ 可能有多种取值，但 \\*\\*\\*\\*\\*1317 只关心其中**字典序最小**的。他想要让你给出**字典序最小**的合法的 $a_1,a_2,...,a_n$ 的取值。"},{"title":"输入格式","type":"input_format","format":"markdown","require":["katex"],"content":"第一行一个正整数 $n$，表示城市的个数。  \r\n接下来 $n-1$ 行，每行两个正整数 $u,v$，表示有一条连接 $u,v$ 的双向道路（$1\\leq u,v\\leq n,u\\neq v$）。"},{"title":"输出格式","type":"output_format","format":"markdown","require":["katex"],"content":"如果合法的 $a_1,a_2,...,a_n$ 不存在，那么输出 `-1`。  \r\n否则输出**字典序最小**的合法的 $a_1,a_2,...,a_n$。"},{"title":"样例","type":"example","format":"markdown","require":["katex"],"content":"#### 样例输入 1\r\n```plain\r\n4\r\n3 1\r\n1 2\r\n4 2\r\n```\r\n\r\n#### 样例输出 1\r\n```plain\r\n3 2 4 1\r\n```\r\n\r\n#### 样例解释 1\r\n容易验证，当城市按危险度从小到大排列为 $3,2,4,1$，即各个城市的危险程度从小到大的排名分别为 $4,2,1,3$ 时 1 号城市与 2 号，3 号城市相连，因此 1 号城市的庇护所为 3 号城市。\r\n同样的 2 号城市的庇护所为 4 号城市， 3 号城市的庇护所为1号城市，4 号城市的庇护所为 2 号城市。这时候就满足任意两个不同城市的庇护所不同。\r\n\r\n#### 样例输入 2\r\n```plain\r\n10\r\n5 1\r\n5 6\r\n3 6\r\n7 4\r\n8 2\r\n9 8\r\n9 4\r\n1 8\r\n7 10\r\n```\r\n\r\n#### 样例输出 2\r\n```plain\r\n2 1 3 5 6 9 7 10 4 8 \r\n```"},{"title":"数据范围与提示","type":"limit_and_hint","format":"markdown","require":["katex"],"content":"对于所有数据，$1\\leq n\\leq 5\\times 10^5$。\r\n\r\n|Subtask #|分值|$n$|特殊限制|\r\n|:-:|:-:|:-:|:-:|\r\n|1|$15$|$1\\leq n\\leq 10$|无|\r\n|2|$30$|$1\\leq n\\leq 2000$|无|\r\n|3|$10$|$1\\leq n\\leq 5\\times 10^5$|每条道路满足 $v-u=1$|\r\n|4|$45$|$1\\leq n\\leq 5\\times 10^5$|无|\r\n"}]}