{"title":"「雅礼集训 2017 Day7」蛐蛐国的修墙方案","time_limit":2000,"memory_limit":1024,"tags":["2017","雅礼集训","搜索"],"operation":{"submit":"https://loj.ac/problem/6043#submit_code","submissions":"https://loj.ac/submissions?problem_id=6043","statistics":"https://loj.ac/problem/6043/statistics/fastest","testdata":"https://loj.ac/problem/6043/testdata","discussion":"https://loj.ac/discussion/problem/6043"},"statement":[{"title":"题目描述","type":"description","format":"markdown","require":["katex"],"content":"Do you wanna build a wall?\r\n\r\n在离跳蚤国很远的地方有一个蛐蛐国，最近蛐蛐国选出了一位新的领导人。\r\n\r\n这位领导人上任之后做的第一件事，就是在蛐蛐国和它的一个邻国 —— 蝈蝈国之间修一堵围墙。\r\n\r\n围墙可以看成是一个长度为 $ n $ 的括号序列，与此同时还有一个长度为 $ n $ 的排列 $ P $，一个围墙被称为稳的，当且仅当：\r\n\r\n1. 这个括号序列是合法的；\r\n2. 构造一张 $ n $ 个点的图，当且仅当第 $ i $ 个位置是左括号时，点 $ i $ 向点 $ P_i $ 连边，最后形成的图必须满足每个点的度数均为一。\r\n\r\n保证对于任意 $ i $ 有 $ i \\neq P_i $。\r\n\r\n一个括号序列合法的定义如下：\r\n\r\n1. 空序列是合法的；\r\n2. 如果 $ A $ 是合法的，那么 $ \\texttt{(}A\\texttt{)} $ 也是合法的；\r\n3. 如果 $ A $ 和 $ B $ 都是合法的，那么 $ AB $ 也是合法的。\r\n\r\n例如 $ \\texttt{()()((()()))} $ 是合法的，而 $ \\texttt{())(()} $ 不是。\r\n\r\n现在蛐蛐国的领导人想知道一种合法的修墙方案。"},{"title":"输入格式","type":"input_format","format":"markdown","require":["katex"],"content":"第一行一个整数 $ n $，表示括号序列的长度。\r\n\r\n接下来一行 $ n $ 个正整数表示排列 $ P_i $。"},{"title":"输出格式","type":"output_format","format":"markdown","require":["katex"],"content":"输出一行一个长度为 $ n $ 的括号序列，如果有多种解，输出任意一种即可。\r\n\r\n**注意，样例输出只是一种参考解，解可能并不唯一。**"},{"title":"样例","type":"example","format":"markdown","require":["katex"],"content":"#### 样例输入 1\r\n```plain\r\n6\r\n2 3 6 1 4 5\r\n```\r\n\r\n#### 样例输出 1\r\n```plain\r\n()()()\r\n```"},{"title":"数据范围与提示","type":"limit_and_hint","format":"markdown","require":["katex"],"content":"本题有三个子任务，只有通过一个子任务中的全部测试点才能获得该子任务的所有分数。\r\n\r\n子任务 1：$ n = 20 $，10 分；  \r\n子任务 2：$ n = 40 $，30 分；  \r\n子任务 3：$ n = 100 $，60 分。"}]}